laviewset/__init__.py
laviewset/_compat.py
laviewset/routes.py
laviewset/views.py
LAViewSet-0.0.1.dist-info/LICENSE.txt
LAViewSet-0.0.1.dist-info/METADATA
LAViewSet-0.0.1.dist-info/WHEEL
LAViewSet-0.0.1.dist-info/top_level.txt
LAViewSet-0.0.1.dist-info/RECORD
