Metadata-Version: 2.1
Name: LAViewSet
Version: 0.0.1
Summary: A Lyte (light) Async Viewset.
Home-page: https://github.com/Algebra8/LAViewSet
Author: Milad M. Nasrollahi
Author-email: milad.m.nasr@gmail.com
License: UNKNOWN
Platform: UNKNOWN
Classifier: License :: OSI Approved :: MIT License
Classifier: Development Status :: 2 - Pre-Alpha
Classifier: Operating System :: OS Independent
Classifier: Programming Language :: Python
Classifier: Programming Language :: Python :: 3
Classifier: Programming Language :: Python :: 3.7
Classifier: Intended Audience :: Developers
Requires-Python: >=3.7
Requires-Dist: aiohttp
